[
  {
    "type": "floor",
    "pos": [
      0,
      0,
      0
    ],
    "rot": [
      0,
      0,
      0
    ],
    "size": [
      500,
      500
    ]
  },
  {
    "type": "wall",
    "pos": [
      0,
      0.5,
      0
    ],
    "rot": [
      0,
      0,
      0
    ],
    "size": [
      40,
      1,
      300
    ]
  },
  {
    "type": "pillar",
    "pos": [
      -20,
      10,
      -100
    ],
    "rot": [
      0,
      0,
      0
    ],
    "size": [
      4,
      20,
      4
    ]
  },
  {
    "type": "pillar",
    "pos": [
      20,
      10,
      -100
    ],
    "rot": [
      0,
      0,
      0
    ],
    "size": [
      4,
      20,
      4
    ]
  },
  {
    "type": "pillar",
    "pos": [
      -20,
      10,
      0
    ],
    "rot": [
      0,
      0,
      0
    ],
    "size": [
      4,
      20,
      4
    ]
  },
  {
    "type": "pillar",
    "pos": [
      20,
      10,
      0
    ],
    "rot": [
      0,
      0,
      0
    ],
    "size": [
      4,
      20,
      4
    ]
  },
  {
    "type": "pillar",
    "pos": [
      -20,
      10,
      100
    ],
    "rot": [
      0,
      0,
      0
    ],
    "size": [
      4,
      20,
      4
    ]
  },
  {
    "type": "pillar",
    "pos": [
      20,
      10,
      100
    ],
    "rot": [
      0,
      0,
      0
    ],
    "size": [
      4,
      20,
      4
    ]
  },
  {
    "type": "wall",
    "pos": [
      0,
      20,
      -100
    ],
    "rot": [
      0,
      0,
      0
    ],
    "size": [
      44,
      2,
      4
    ]
  },
  {
    "type": "wall",
    "pos": [
      0,
      20,
      0
    ],
    "rot": [
      0,
      0,
      0
    ],
    "size": [
      44,
      2,
      4
    ]
  },
  {
    "type": "wall",
    "pos": [
      0,
      20,
      100
    ],
    "rot": [
      0,
      0,
      0
    ],
    "size": [
      44,
      2,
      4
    ]
  },
  {
    "type": "fence",
    "pos": [
      -19.5,
      2.5,
      0
    ],
    "rot": [
      0,
      0,
      0
    ],
    "size": [
      2,
      300,
      1
    ]
  },
  {
    "type": "fence",
    "pos": [
      19.5,
      2.5,
      0
    ],
    "rot": [
      0,
      0,
      0
    ],
    "size": [
      2,
      300,
      1
    ]
  },
  {
    "type": "vehicle",
    "pos": [
      -10,
      1.5,
      -40
    ],
    "rot": [
      0,
      0.4,
      0
    ],
    "size": [
      4,
      2.5,
      8
    ]
  },
  {
    "type": "vehicle",
    "pos": [
      8,
      1.5,
      -20
    ],
    "rot": [
      0,
      -0.2,
      0
    ],
    "size": [
      4,
      2.5,
      8
    ]
  },
  {
    "type": "vehicle",
    "pos": [
      -5,
      1.5,
      10
    ],
    "rot": [
      0,
      3.14,
      0
    ],
    "size": [
      4,
      2.5,
      8
    ]
  },
  {
    "type": "vehicle",
    "pos": [
      12,
      1.5,
      45
    ],
    "rot": [
      0,
      0.8,
      0
    ],
    "size": [
      4,
      2.5,
      8
    ]
  },
  {
    "type": "vehicle",
    "pos": [
      -8,
      2,
      -120
    ],
    "rot": [
      0,
      0,
      0
    ],
    "size": [
      5,
      4,
      12
    ]
  },
  {
    "type": "openContainer",
    "pos": [
      15,
      2.5,
      -70
    ],
    "rot": [
      0,
      -0.5,
      0
    ],
    "size": [
      6,
      4,
      12
    ]
  },
  {
    "type": "openContainer",
    "pos": [
      -15,
      2.5,
      80
    ],
    "rot": [
      0,
      0.2,
      0
    ],
    "size": [
      6,
      4,
      12
    ]
  },
  {
    "type": "crate",
    "pos": [
      -5,
      1.5,
      -60
    ],
    "rot": [
      0,
      0.5,
      0
    ],
    "size": [
      3,
      3,
      3
    ]
  },
  {
    "type": "crate",
    "pos": [
      -5,
      1.5,
      -63
    ],
    "rot": [
      0,
      0.1,
      0
    ],
    "size": [
      3,
      3,
      3
    ]
  },
  {
    "type": "crate",
    "pos": [
      7,
      1.5,
      20
    ],
    "rot": [
      0,
      -0.3,
      0
    ],
    "size": [
      3,
      3,
      3
    ]
  },
  {
    "type": "barrel",
    "pos": [
      10,
      0.5,
      -30
    ],
    "rot": [
      0,
      0,
      0
    ],
    "size": [
      1,
      1.2,
      1
    ]
  },
  {
    "type": "barrel",
    "pos": [
      11,
      0.5,
      -31
    ],
    "rot": [
      0,
      0,
      0
    ],
    "size": [
      1,
      1.2,
      1
    ]
  },
  {
    "type": "barrel",
    "pos": [
      -12,
      0.5,
      15
    ],
    "rot": [
      0,
      0,
      0
    ],
    "size": [
      1,
      1.2,
      1
    ]
  },
  {
    "type": "vendingMachine",
    "pos": [
      -18,
      1.5,
      -50
    ],
    "rot": [
      0,
      1.57,
      0
    ],
    "size": [
      1.5,
      3,
      1
    ]
  },
  {
    "type": "vendingMachine",
    "pos": [
      18,
      1.5,
      30
    ],
    "rot": [
      0,
      -1.57,
      0
    ],
    "size": [
      1.5,
      3,
      1
    ]
  },
  {
    "type": "platform",
    "pos": [
      -20,
      5,
      -80
    ],
    "rot": [
      0,
      0,
      0
    ],
    "size": [
      6,
      0.5,
      10
    ]
  },
  {
    "type": "platform",
    "pos": [
      20,
      8,
      20
    ],
    "rot": [
      0,
      0,
      0
    ],
    "size": [
      6,
      0.5,
      10
    ]
  },
  {
    "type": "coverWall",
    "pos": [
      0,
      1.5,
      -100
    ],
    "rot": [
      0,
      0,
      0
    ],
    "size": [
      10,
      2,
      0.5
    ]
  },
  {
    "type": "coverWall",
    "pos": [
      0,
      1.5,
      100
    ],
    "rot": [
      0,
      0,
      0
    ],
    "size": [
      10,
      2,
      0.5
    ]
  }
]